followsphere/__init__.py
followsphere/__main__.py
followsphere/data.json
followsphere/linkedin.py
followsphere/utils.py
followsphere-0.1.7.dist-info/LICENSE
followsphere-0.1.7.dist-info/METADATA
followsphere-0.1.7.dist-info/WHEEL
followsphere-0.1.7.dist-info/entry_points.txt
followsphere-0.1.7.dist-info/RECORD
