Metadata-Version: 2.1
Name: followsphere
Version: 0.1.7
Summary: Streamline your hashtag following and stay on top of trends effortlessly
Author: hyperoot
Author-email: rajesh@hyperoot.dev
Requires-Python: >=3.12,<4.0
Classifier: Programming Language :: Python :: 3
Classifier: Programming Language :: Python :: 3.12
Classifier: Programming Language :: Python :: 3.13
Requires-Dist: beaupy (>=3.9.1,<4.0.0)
Requires-Dist: playwright (>=1.44.0,<2.0.0)
Requires-Dist: pyfiglet (>=1.0.2,<2.0.0)
Requires-Dist: rich (>=13.7.1,<14.0.0)
Requires-Dist: termcolor (>=2.4.0,<3.0.0)
Requires-Dist: typer (>=0.12.3,<0.13.0)
